Workbook

Sheet PAINEL
A1: 🐂 704 AGRO — PAINEL DA FAZENDA
B3: REBANHO | E3: DINHEIRO
B4: Cabeças compradas | C4: =SUM(COMPRAS!E:E) | E4: Investido nas compras | F4: =SUM(COMPRAS!L:L)
B5: Cabeças vendidas | C5: =SUM(VENDAS!D:D) | E5: Recebido nas vendas | F5: =SUM(VENDAS!K:K)
B6: No pasto agora | C6: =C4-C5 | E6: Resultado | F6: =F5-F4
B7: Peso comprado | C7: =SUM(COMPRAS!F:F) | E7: Saldo em caixa | F7: =SUM(CAIXA!F:F)-SUM(CAIXA!G:G)
B8: Peso vendido | C8: =SUM(VENDAS!E:E) | E8: @ média de compra | F8: =IFERROR(SUM(COMPRAS!L:L)/SUM(COMPRAS!H:H),0)
B9: Lotes abertos | C9: =COUNTIF(LOTES!L:L,"ABERTO") | E9: @ média de venda | F9: =IFERROR(SUM(VENDAS!I:I)/SUM(VENDAS!G:G),0)
B11: MARGEM POR ARROBA
B12: Ganho por @ (venda − compra) | C12: =F9-F8
B14: Os números acima se calculam sozinhos. Você só preenche as abas COMPRAS, VENDAS e CAIXA — e a aba PESAGENS recebe o que vem do aplicativo.
B16: THIAGO PORTO 704 AGRO — Compra e venda de bovinos · (77) 99922-6268

Sheet COMPRAS
A1: 📥 COMPRAS — gado que entrou
A2: DATA | B2: LOTE | C2: FORNECEDOR | D2: TIPO | E2: CABEÇAS | F2: PESO NA BALANÇA | G2: RENDIMENTO | H2: ARROBAS | I2: R$/@ | J2: VALOR DO GADO | K2: FRETE + COMISSÃO | L2: CUSTO TOTAL | M2: OBSERVAÇÃO
G3: 0.52 | H3: =IF(F3="","",F3*G3/15) | J3: =IF(H3="","",H3*I3) | L3: =IF(J3="","",J3+N(K3))
G4: 0.52 | H4: =IF(F4="","",F4*G4/15) | J4: =IF(H4="","",H4*I4) | L4: =IF(J4="","",J4+N(K4))
G5: 0.52 | H5: =IF(F5="","",F5*G5/15) | J5: =IF(H5="","",H5*I5) | L5: =IF(J5="","",J5+N(K5))
G6: 0.52 | H6: =IF(F6="","",F6*G6/15) | J6: =IF(H6="","",H6*I6) | L6: =IF(J6="","",J6+N(K6))
G7: 0.52 | H7: =IF(F7="","",F7*G7/15) | J7: =IF(H7="","",H7*I7) | L7: =IF(J7="","",J7+N(K7))
G8: 0.52 | H8: =IF(F8="","",F8*G8/15) | J8: =IF(H8="","",H8*I8) | L8: =IF(J8="","",J8+N(K8))
G9: 0.52 | H9: =IF(F9="","",F9*G9/15) | J9: =IF(H9="","",H9*I9) | L9: =IF(J9="","",J9+N(K9))
G10: 0.52 | H10: =IF(F10="","",F10*G10/15) | J10: =IF(H10="","",H10*I10) | L10: =IF(J10="","",J10+N(K10))
G11: 0.52 | H11: =IF(F11="","",F11*G11/15) | J11: =IF(H11="","",H11*I11) | L11: =IF(J11="","",J11+N(K11))
G12: 0.52 | H12: =IF(F12="","",F12*G12/15) | J12: =IF(H12="","",H12*I12) | L12: =IF(J12="","",J12+N(K12))
G13: 0.52 | H13: =IF(F13="","",F13*G13/15) | J13: =IF(H13="","",H13*I13) | L13: =IF(J13="","",J13+N(K13))
G14: 0.52 | H14: =IF(F14="","",F14*G14/15) | J14: =IF(H14="","",H14*I14) | L14: =IF(J14="","",J14+N(K14))
... G302: 0.52 | H302: =IF(F302="","",F302*G302/15) | J302: =IF(H302="","",H302*I302) | L302: =IF(J302="","",J302+N(K302))

Sheet PESAGENS
A1: ⚖️ PESAGENS — vem do aplicativo (ou digite à mão)
A2: DATA | B2: LOTE | C2: VENDEDOR / ORIGEM | D2: Nº DO BRINCO | E2: CABEÇAS | F2: PESO NA BALANÇA | G2: DESCONTO POR CAB. | H2: PESO LÍQUIDO | I2: RENDIMENTO | J2: ARROBAS | K2: R$/@ | L2: VALOR
H3: =IF(F3="","",MAX(0,F3-N(G3)*N(E3))) | I3: 0.52 | J3: =IF(H3="","",H3*N(I3)/15) | L3: =IF(J3="","",J3*N(K3))
H4: =IF(F4="","",MAX(0,F4-N(G4)*N(E4))) | I4: 0.52 | J4: =IF(H4="","",H4*N(I4)/15) | L4: =IF(J4="","",J4*N(K4))
H5: =IF(F5="","",MAX(0,F5-N(G5)*N(E5))) | I5: 0.52 | J5: =IF(H5="","",H5*N(I5)/15) | L5: =IF(J5="","",J5*N(K5))
H6: =IF(F6="","",MAX(0,F6-N(G6)*N(E6))) | I6: 0.52 | J6: =IF(H6="","",H6*N(I6)/15) | L6: =IF(J6="","",J6*N(K6))
H7: =IF(F7="","",MAX(0,F7-N(G7)*N(E7))) | I7: 0.52 | J7: =IF(H7="","",H7*N(I7)/15) | L7: =IF(J7="","",J7*N(K7))
H8: =IF(F8="","",MAX(0,F8-N(G8)*N(E8))) | I8: 0.52 | J8: =IF(H8="","",H8*N(I8)/15) | L8: =IF(J8="","",J8*N(K8))
H9: =IF(F9="","",MAX(0,F9-N(G9)*N(E9))) | I9: 0.52 | J9: =IF(H9="","",H9*N(I9)/15) | L9: =IF(J9="","",J9*N(K9))
H10: =IF(F10="","",MAX(0,F10-N(G10)*N(E10))) | I10: 0.52 | J10: =IF(H10="","",H10*N(I10)/15) | L10: =IF(J10="","",J10*N(K10))
H11: =IF(F11="","",MAX(0,F11-N(G11)*N(E11))) | I11: 0.52 | J11: =IF(H11="","",H11*N(I11)/15) | L11: =IF(J11="","",J11*N(K11))
H12: =IF(F12="","",MAX(0,F12-N(G12)*N(E12))) | I12: 0.52 | J12: =IF(H12="","",H12*N(I12)/15) | L12: =IF(J12="","",J12*N(K12))
H13: =IF(F13="","",MAX(0,F13-N(G13)*N(E13))) | I13: 0.52 | J13: =IF(H13="","",H13*N(I13)/15) | L13: =IF(J13="","",J13*N(K13))
H14: =IF(F14="","",MAX(0,F14-N(G14)*N(E14))) | I14: 0.52 | J14: =IF(H14="","",H14*N(I14)/15) | L14: =IF(J14="","",J14*N(K14))
... H302: =IF(F302="","",MAX(0,F302-N(G302)*N(E302))) | I302: 0.52 | J302: =IF(H302="","",H302*N(I302)/15) | L302: =IF(J302="","",J302*N(K302))

Sheet VENDAS
A1: 📤 VENDAS — gado que saiu
A2: DATA | B2: LOTE | C2: COMPRADOR | D2: CABEÇAS | E2: PESO NA BALANÇA | F2: RENDIMENTO | G2: ARROBAS | H2: R$/@ | I2: VALOR BRUTO | J2: FRETE + COMISSÃO | K2: VALOR LÍQUIDO | L2: OBSERVAÇÃO
F3: 0.52 | G3: =IF(E3="","",E3*F3/15) | I3: =IF(G3="","",G3*H3) | K3: =IF(I3="","",I3-N(J3))
F4: 0.52 | G4: =IF(E4="","",E4*F4/15) | I4: =IF(G4="","",G4*H4) | K4: =IF(I4="","",I4-N(J4))
F5: 0.52 | G5: =IF(E5="","",E5*F5/15) | I5: =IF(G5="","",G5*H5) | K5: =IF(I5="","",I5-N(J5))
F6: 0.52 | G6: =IF(E6="","",E6*F6/15) | I6: =IF(G6="","",G6*H6) | K6: =IF(I6="","",I6-N(J6))
F7: 0.52 | G7: =IF(E7="","",E7*F7/15) | I7: =IF(G7="","",G7*H7) | K7: =IF(I7="","",I7-N(J7))
F8: 0.52 | G8: =IF(E8="","",E8*F8/15) | I8: =IF(G8="","",G8*H8) | K8: =IF(I8="","",I8-N(J8))
F9: 0.52 | G9: =IF(E9="","",E9*F9/15) | I9: =IF(G9="","",G9*H9) | K9: =IF(I9="","",I9-N(J9))
F10: 0.52 | G10: =IF(E10="","",E10*F10/15) | I10: =IF(G10="","",G10*H10) | K10: =IF(I10="","",I10-N(J10))
F11: 0.52 | G11: =IF(E11="","",E11*F11/15) | I11: =IF(G11="","",G11*H11) | K11: =IF(I11="","",I11-N(J11))
F12: 0.52 | G12: =IF(E12="","",E12*F12/15) | I12: =IF(G12="","",G12*H12) | K12: =IF(I12="","",I12-N(J12))
F13: 0.52 | G13: =IF(E13="","",E13*F13/15) | I13: =IF(G13="","",G13*H13) | K13: =IF(I13="","",I13-N(J13))
F14: 0.52 | G14: =IF(E14="","",E14*F14/15) | I14: =IF(G14="","",G14*H14) | K14: =IF(I14="","",I14-N(J14))
... F302: 0.52 | G302: =IF(E302="","",E302*F302/15) | I302: =IF(G302="","",G302*H302) | K302: =IF(I302="","",I302-N(J302))

Sheet LOTES
A1: 🐄 LOTES — cada lote do começo ao fim
A2: LOTE | B2: ENTROU EM | C2: SAIU EM | D2: DIAS NO PASTO | E2: CABEÇAS QUE ENTRARAM | F2: CABEÇAS QUE SAÍRAM | G2: PESO DE ENTRADA | H2: PESO DE SAÍDA | I2: GANHO DE PESO | J2: CUSTO | K2: RECEITA | L2: SITUAÇÃO | M2: LUCRO
B3: =IF(OR($A3="",COUNTIF(COMPRAS!$B:$B,$A3)=0),"",MINIFS(COMPRAS!$A:$A,COMPRAS!$B:$B,$A3)) | C3: =IF(OR($A3="",COUNTIF(VENDAS!$B:$B,$A3)=0),"",MAXIFS(VENDAS!$A:$A,VENDAS!$B:$B,$A3)) | D3: =IF(OR($A3="",B3=""),"",IF(C3="",TODAY()-B3,C3-B3)) | E3: =IF($A3="","",SUMIF(COMPRAS!$B:$B,$A3,COMPRAS!$E:$E)) | F3: =IF($A3="","",SUMIF(VENDAS!$B:$B,$A3,VENDAS!$D:$D)) | G3: =IF($A3="","",SUMIF(COMPRAS!$B:$B,$A3,COMPRAS!$F:$F)) | H3: =IF($A3="","",SUMIF(VENDAS!$B:$B,$A3,VENDAS!$E:$E)) | I3: =IF($A3="","",H3-G3) | J3: =IF($A3="","",SUMIF(COMPRAS!$B:$B,$A3,COMPRAS!$L:$L)) | K3: =IF($A3="","",SUMIF(VENDAS!$B:$B,$A3,VENDAS!$K:$K)) | L3: =IF($A3="","",IF(F3>=E3,"FECHADO","ABERTO")) | M3: =IF($A3="","",K3-J3)
B4: =IF(OR($A4="",COUNTIF(COMPRAS!$B:$B,$A4)=0),"",MINIFS(COMPRAS!$A:$A,COMPRAS!$B:$B,$A4)) | C4: =IF(OR($A4="",COUNTIF(VENDAS!$B:$B,$A4)=0),"",MAXIFS(VENDAS!$A:$A,VENDAS!$B:$B,$A4)) | D4: =IF(OR($A4="",B4=""),"",IF(C4="",TODAY()-B4,C4-B4)) | E4: =IF($A4="","",SUMIF(COMPRAS!$B:$B,$A4,COMPRAS!$E:$E)) | F4: =IF($A4="","",SUMIF(VENDAS!$B:$B,$A4,VENDAS!$D:$D)) | G4: =IF($A4="","",SUMIF(COMPRAS!$B:$B,$A4,COMPRAS!$F:$F)) | H4: =IF($A4="","",SUMIF(VENDAS!$B:$B,$A4,VENDAS!$E:$E)) | I4: =IF($A4="","",H4-G4) | J4: =IF($A4="","",SUMIF(COMPRAS!$B:$B,$A4,COMPRAS!$L:$L)) | K4: =IF($A4="","",SUMIF(VENDAS!$B:$B,$A4,VENDAS!$K:$K)) | L4: =IF($A4="","",IF(F4>=E4,"FECHADO","ABERTO")) | M4: =IF($A4="","",K4-J4)
B5: =IF(OR($A5="",COUNTIF(COMPRAS!$B:$B,$A5)=0),"",MINIFS(COMPRAS!$A:$A,COMPRAS!$B:$B,$A5)) | C5: =IF(OR($A5="",COUNTIF(VENDAS!$B:$B,$A5)=0),"",MAXIFS(VENDAS!$A:$A,VENDAS!$B:$B,$A5)) | D5: =IF(OR($A5="",B5=""),"",IF(C5="",TODAY()-B5,C5-B5)) | E5: =IF($A5="","",SUMIF(COMPRAS!$B:$B,$A5,COMPRAS!$E:$E)) | F5: =IF($A5="","",SUMIF(VENDAS!$B:$B,$A5,VENDAS!$D:$D)) | G5: =IF($A5="","",SUMIF(COMPRAS!$B:$B,$A5,COMPRAS!$F:$F)) | H5: =IF($A5="","",SUMIF(VENDAS!$B:$B,$A5,VENDAS!$E:$E)) | I5: =IF($A5="","",H5-G5) | J5: =IF($A5="","",SUMIF(COMPRAS!$B:$B,$A5,COMPRAS!$L:$L)) | K5: =IF($A5="","",SUMIF(VENDAS!$B:$B,$A5,VENDAS!$K:$K)) | L5: =IF($A5="","",IF(F5>=E5,"FECHADO","ABERTO")) | M5: =IF($A5="","",K5-J5)
B6: =IF(OR($A6="",COUNTIF(COMPRAS!$B:$B,$A6)=0),"",MINIFS(COMPRAS!$A:$A,COMPRAS!$B:$B,$A6)) | C6: =IF(OR($A6="",COUNTIF(VENDAS!$B:$B,$A6)=0),"",MAXIFS(VENDAS!$A:$A,VENDAS!$B:$B,$A6)) | D6: =IF(OR($A6="",B6=""),"",IF(C6="",TODAY()-B6,C6-B6)) | E6: =IF($A6="","",SUMIF(COMPRAS!$B:$B,$A6,COMPRAS!$E:$E)) | F6: =IF($A6="","",SUMIF(VENDAS!$B:$B,$A6,VENDAS!$D:$D)) | G6: =IF($A6="","",SUMIF(COMPRAS!$B:$B,$A6,COMPRAS!$F:$F)) | H6: =IF($A6="","",SUMIF(VENDAS!$B:$B,$A6,VENDAS!$E:$E)) | I6: =IF($A6="","",H6-G6) | J6: =IF($A6="","",SUMIF(COMPRAS!$B:$B,$A6,COMPRAS!$L:$L)) | K6: =IF($A6="","",SUMIF(VENDAS!$B:$B,$A6,VENDAS!$K:$K)) | L6: =IF($A6="","",IF(F6>=E6,"FECHADO","ABERTO")) | M6: =IF($A6="","",K6-J6)
B7: =IF(OR($A7="",COUNTIF(COMPRAS!$B:$B,$A7)=0),"",MINIFS(COMPRAS!$A:$A,COMPRAS!$B:$B,$A7)) | C7: =IF(OR($A7="",COUNTIF(VENDAS!$B:$B,$A7)=0),"",MAXIFS(VENDAS!$A:$A,VENDAS!$B:$B,$A7)) | D7: =IF(OR($A7="",B7=""),"",IF(C7="",TODAY()-B7,C7-B7)) | E7: =IF($A7="","",SUMIF(COMPRAS!$B:$B,$A7,COMPRAS!$E:$E)) | F7: =IF($A7="","",SUMIF(VENDAS!$B:$B,$A7,VENDAS!$D:$D)) | G7: =IF($A7="","",SUMIF(COMPRAS!$B:$B,$A7,COMPRAS!$F:$F)) | H7: =IF($A7="","",SUMIF(VENDAS!$B:$B,$A7,VENDAS!$E:$E)) | I7: =IF($A7="","",H7-G7) | J7: =IF($A7="","",SUMIF(COMPRAS!$B:$B,$A7,COMPRAS!$L:$L)) | K7: =IF($A7="","",SUMIF(VENDAS!$B:$B,$A7,VENDAS!$K:$K)) | L7: =IF($A7="","",IF(F7>=E7,"FECHADO","ABERTO")) | M7: =IF($A7="","",K7-J7)
B8: =IF(OR($A8="",COUNTIF(COMPRAS!$B:$B,$A8)=0),"",MINIFS(COMPRAS!$A:$A,COMPRAS!$B:$B,$A8)) | C8: =IF(OR($A8="",COUNTIF(VENDAS!$B:$B,$A8)=0),"",MAXIFS(VENDAS!$A:$A,VENDAS!$B:$B,$A8)) | D8: =IF(OR($A8="",B8=""),"",IF(C8="",TODAY()-B8,C8-B8)) | E8: =IF($A8="","",SUMIF(COMPRAS!$B:$B,$A8,COMPRAS!$E:$E)) | F8: =IF($A8="","",SUMIF(VENDAS!$B:$B,$A8,VENDAS!$D:$D)) | G8: =IF($A8="","",SUMIF(COMPRAS!$B:$B,$A8,COMPRAS!$F:$F)) | H8: =IF($A8="","",SUMIF(VENDAS!$B:$B,$A8,VENDAS!$E:$E)) | I8: =IF($A8="","",H8-G8) | J8: =IF($A8="","",SUMIF(COMPRAS!$B:$B,$A8,COMPRAS!$L:$L)) | K8: =IF($A8="","",SUMIF(VENDAS!$B:$B,$A8,VENDAS!$K:$K)) | L8: =IF($A8="","",IF(F8>=E8,"FECHADO","ABERTO")) | M8: =IF($A8="","",K8-J8)
B9: =IF(OR($A9="",COUNTIF(COMPRAS!$B:$B,$A9)=0),"",MINIFS(COMPRAS!$A:$A,COMPRAS!$B:$B,$A9)) | C9: =IF(OR($A9="",COUNTIF(VENDAS!$B:$B,$A9)=0),"",MAXIFS(VENDAS!$A:$A,VENDAS!$B:$B,$A9)) | D9: =IF(OR($A9="",B9=""),"",IF(C9="",TODAY()-B9,C9-B9)) | E9: =IF($A9="","",SUMIF(COMPRAS!$B:$B,$A9,COMPRAS!$E:$E)) | F9: =IF($A9="","",SUMIF(VENDAS!$B:$B,$A9,VENDAS!$D:$D)) | G9: =IF($A9="","",SUMIF(COMPRAS!$B:$B,$A9,COMPRAS!$F:$F)) | H9: =IF($A9="","",SUMIF(VENDAS!$B:$B,$A9,VENDAS!$E:$E)) | I9: =IF($A9="","",H9-G9) | J9: =IF($A9="","",SUMIF(COMPRAS!$B:$B,$A9,COMPRAS!$L:$L)) | K9: =IF($A9="","",SUMIF(VENDAS!$B:$B,$A9,VENDAS!$K:$K)) | L9: =IF($A9="","",IF(F9>=E9,"FECHADO","ABERTO")) | M9: =IF($A9="","",K9-J9)
B10: =IF(OR($A10="",COUNTIF(COMPRAS!$B:$B,$A10)=0),"",MINIFS(COMPRAS!$A:$A,COMPRAS!$B:$B,$A10)) | C10: =IF(OR($A10="",COUNTIF(VENDAS!$B:$B,$A10)=0),"",MAXIFS(VENDAS!$A:$A,VENDAS!$B:$B,$A10)) | D10: =IF(OR($A10="",B10=""),"",IF(C10="",TODAY()-B10,C10-B10)) | E10: =IF($A10="","",SUMIF(COMPRAS!$B:$B,$A10,COMPRAS!$E:$E)) | F10: =IF($A10="","",SUMIF(VENDAS!$B:$B,$A10,VENDAS!$D:$D)) | G10: =IF($A10="","",SUMIF(COMPRAS!$B:$B,$A10,COMPRAS!$F:$F)) | H10: =IF($A10="","",SUMIF(VENDAS!$B:$B,$A10,VENDAS!$E:$E)) | I10: =IF($A10="","",H10-G10) | J10: =IF($A10="","",SUMIF(COMPRAS!$B:$B,$A10,COMPRAS!$L:$L)) | K10: =IF($A10="","",SUMIF(VENDAS!$B:$B,$A10,VENDAS!$K:$K)) | L10: =IF($A10="","",IF(F10>=E10,"FECHADO","ABERTO")) | M10: =IF($A10="","",K10-J10)
B11: =IF(OR($A11="",COUNTIF(COMPRAS!$B:$B,$A11)=0),"",MINIFS(COMPRAS!$A:$A,COMPRAS!$B:$B,$A11)) | C11: =IF(OR($A11="",COUNTIF(VENDAS!$B:$B,$A11)=0),"",MAXIFS(VENDAS!$A:$A,VENDAS!$B:$B,$A11)) | D11: =IF(OR($A11="",B11=""),"",IF(C11="",TODAY()-B11,C11-B11)) | E11: =IF($A11="","",SUMIF(COMPRAS!$B:$B,$A11,COMPRAS!$E:$E)) | F11: =IF($A11="","",SUMIF(VENDAS!$B:$B,$A11,VENDAS!$D:$D)) | G11: =IF($A11="","",SUMIF(COMPRAS!$B:$B,$A11,COMPRAS!$F:$F)) | H11: =IF($A11="","",SUMIF(VENDAS!$B:$B,$A11,VENDAS!$E:$E)) | I11: =IF($A11="","",H11-G11) | J11: =IF($A11="","",SUMIF(COMPRAS!$B:$B,$A11,COMPRAS!$L:$L)) | K11: =IF($A11="","",SUMIF(VENDAS!$B:$B,$A11,VENDAS!$K:$K)) | L11: =IF($A11="","",IF(F11>=E11,"FECHADO","ABERTO")) | M11: =IF($A11="","",K11-J11)
B12: =IF(OR($A12="",COUNTIF(COMPRAS!$B:$B,$A12)=0),"",MINIFS(COMPRAS!$A:$A,COMPRAS!$B:$B,$A12)) | C12: =IF(OR($A12="",COUNTIF(VENDAS!$B:$B,$A12)=0),"",MAXIFS(VENDAS!$A:$A,VENDAS!$B:$B,$A12)) | D12: =IF(OR($A12="",B12=""),"",IF(C12="",TODAY()-B12,C12-B12)) | E12: =IF($A12="","",SUMIF(COMPRAS!$B:$B,$A12,COMPRAS!$E:$E)) | F12: =IF($A12="","",SUMIF(VENDAS!$B:$B,$A12,VENDAS!$D:$D)) | G12: =IF($A12="","",SUMIF(COMPRAS!$B:$B,$A12,COMPRAS!$F:$F)) | H12: =IF($A12="","",SUMIF(VENDAS!$B:$B,$A12,VENDAS!$E:$E)) | I12: =IF($A12="","",H12-G12) | J12: =IF($A12="","",SUMIF(COMPRAS!$B:$B,$A12,COMPRAS!$L:$L)) | K12: =IF($A12="","",SUMIF(VENDAS!$B:$B,$A12,VENDAS!$K:$K)) | L12: =IF($A12="","",IF(F12>=E12,"FECHADO","ABERTO")) | M12: =IF($A12="","",K12-J12)
B13: =IF(OR($A13="",COUNTIF(COMPRAS!$B:$B,$A13)=0),"",MINIFS(COMPRAS!$A:$A,COMPRAS!$B:$B,$A13)) | C13: =IF(OR($A13="",COUNTIF(VENDAS!$B:$B,$A13)=0),"",MAXIFS(VENDAS!$A:$A,VENDAS!$B:$B,$A13)) | D13: =IF(OR($A13="",B13=""),"",IF(C13="",TODAY()-B13,C13-B13)) | E13: =IF($A13="","",SUMIF(COMPRAS!$B:$B,$A13,COMPRAS!$E:$E)) | F13: =IF($A13="","",SUMIF(VENDAS!$B:$B,$A13,VENDAS!$D:$D)) | G13: =IF($A13="","",SUMIF(COMPRAS!$B:$B,$A13,COMPRAS!$F:$F)) | H13: =IF($A13="","",SUMIF(VENDAS!$B:$B,$A13,VENDAS!$E:$E)) | I13: =IF($A13="","",H13-G13) | J13: =IF($A13="","",SUMIF(COMPRAS!$B:$B,$A13,COMPRAS!$L:$L)) | K13: =IF($A13="","",SUMIF(VENDAS!$B:$B,$A13,VENDAS!$K:$K)) | L13: =IF($A13="","",IF(F13>=E13,"FECHADO","ABERTO")) | M13: =IF($A13="","",K13-J13)
B14: =IF(OR($A14="",COUNTIF(COMPRAS!$B:$B,$A14)=0),"",MINIFS(COMPRAS!$A:$A,COMPRAS!$B:$B,$A14)) | C14: =IF(OR($A14="",COUNTIF(VENDAS!$B:$B,$A14)=0),"",MAXIFS(VENDAS!$A:$A,VENDAS!$B:$B,$A14)) | D14: =IF(OR($A14="",B14=""),"",IF(C14="",TODAY()-B14,C14-B14)) | E14: =IF($A14="","",SUMIF(COMPRAS!$B:$B,$A14,COMPRAS!$E:$E)) | F14: =IF($A14="","",SUMIF(VENDAS!$B:$B,$A14,VENDAS!$D:$D)) | G14: =IF($A14="","",SUMIF(COMPRAS!$B:$B,$A14,COMPRAS!$F:$F)) | H14: =IF($A14="","",SUMIF(VENDAS!$B:$B,$A14,VENDAS!$E:$E)) | I14: =IF($A14="","",H14-G14) | J14: =IF($A14="","",SUMIF(COMPRAS!$B:$B,$A14,COMPRAS!$L:$L)) | K14: =IF($A14="","",SUMIF(VENDAS!$B:$B,$A14,VENDAS!$K:$K)) | L14: =IF($A14="","",IF(F14>=E14,"FECHADO","ABERTO")) | M14: =IF($A14="","",K14-J14)
... B302: =IF(OR($A302="",COUNTIF(COMPRAS!$B:$B,$A302)=0),"",MINIFS(COMPRAS!$A:$A,COMPRAS!$B:$B,$A302)) | C302: =IF(OR($A302="",COUNTIF(VENDAS!$B:$B,$A302)=0),"",MAXIFS(VENDAS!$A:$A,VENDAS!$B:$B,$A302)) | D302: =IF(OR($A302="",B302=""),"",IF(C302="",TODAY()-B302,C302-B302)) | E302: =IF($A302="","",SUMIF(COMPRAS!$B:$B,$A302,COMPRAS!$E:$E)) | F302: =IF($A302="","",SUMIF(VENDAS!$B:$B,$A302,VENDAS!$D:$D)) | G302: =IF($A302="","",SUMIF(COMPRAS!$B:$B,$A302,COMPRAS!$F:$F)) | H302: =IF($A302="","",SUMIF(VENDAS!$B:$B,$A302,VENDAS!$E:$E)) | I302: =IF($A302="","",H302-G302) | J302: =IF($A302="","",SUMIF(COMPRAS!$B:$B,$A302,COMPRAS!$L:$L)) | K302: =IF($A302="","",SUMIF(VENDAS!$B:$B,$A302,VENDAS!$K:$K)) | L302: =IF($A302="","",IF(F302>=E302,"FECHADO","ABERTO")) | M302: =IF($A302="","",K302-J302)

Sheet CAIXA
A1: 💰 CAIXA — todo dinheiro que entra e sai
A2: DATA | B2: LOTE | C2: CATEGORIA | D2: DESCRIÇÃO | E2: FORMA | F2: ENTROU | G2: SAIU | H2: SALDO
H3: =IF(AND(F3="",G3=""),"",0+N(F3)-N(G3))
H4: =IF(AND(F4="",G4=""),"",N(H3)+N(F4)-N(G4))
H5: =IF(AND(F5="",G5=""),"",N(H4)+N(F5)-N(G5))
H6: =IF(AND(F6="",G6=""),"",N(H5)+N(F6)-N(G6))
H7: =IF(AND(F7="",G7=""),"",N(H6)+N(F7)-N(G7))
H8: =IF(AND(F8="",G8=""),"",N(H7)+N(F8)-N(G8))
H9: =IF(AND(F9="",G9=""),"",N(H8)+N(F9)-N(G9))
H10: =IF(AND(F10="",G10=""),"",N(H9)+N(F10)-N(G10))
H11: =IF(AND(F11="",G11=""),"",N(H10)+N(F11)-N(G11))
H12: =IF(AND(F12="",G12=""),"",N(H11)+N(F12)-N(G12))
H13: =IF(AND(F13="",G13=""),"",N(H12)+N(F13)-N(G13))
H14: =IF(AND(F14="",G14=""),"",N(H13)+N(F14)-N(G14))
H15: =IF(AND(F15="",G15=""),"",N(H14)+N(F15)-N(G15))
... H302: =IF(AND(F302="",G302=""),"",N(H301)+N(F302)-N(G302))

Sheet COMO USAR
A1: 📖 COMO USAR ESTA PLANILHA
B4: O QUE VOCÊ PREENCHE
B5: COMPRAS — cada vez que comprar gado. Preencha data, lote, fornecedor, cabeças, peso e o preço da arroba. As arrobas, o valor e o custo total se calculam sozinhos.
B6: VENDAS — cada vez que vender. Mesma coisa: o valor líquido já desconta frete e comissão.
B7: CAIXA — todo dinheiro que entra e sai, inclusive o que não é gado (vacina, sal, diária, combustível). O saldo vai somando linha por linha.
B9: O QUE SE PREENCHE SOZINHO
B10: PESAGENS — é aqui que cai o que vem do aplicativo Calculadora de Boi. Você também pode digitar à mão se quiser.
B11: LOTES — junta tudo por lote: quando entrou, quando saiu, quantos dias no pasto, quanto engordou, quanto custou, quanto rendeu e o lucro. Só digite o nome do lote na coluna A — o resto vem sozinho das outras abas.
B12: PAINEL — o resumo da fazenda. Não mexa, só olhe.
B14: HISTÓRICO DE CADA ANIMAL
B15: Com a planilha ligada no aplicativo, aparecem mais três abas, montadas sozinhas a partir da PESAGENS: ANIMAIS, HISTÓRICO e CONSULTA.
B16: ANIMAIS — um animal por linha, pelo número do brinco: peso na 1ª pesagem, peso atual, quanto ganhou desde a pesagem anterior, ganho total e ganho por dia.
B17: HISTÓRICO — todas as pesagens de cada animal, uma embaixo da outra, da mais antiga pra mais nova.
... B31: THIAGO PORTO 704 AGRO — Compra e venda de bovinos · (77) 99922-6268
